argparsecfg/__init__.py
argparsecfg/app.py
argparsecfg/core.py
argparsecfg/test_tools.py
argparsecfg/version.py
argparsecfg-0.2.4.dist-info/LICENSE
argparsecfg-0.2.4.dist-info/METADATA
argparsecfg-0.2.4.dist-info/WHEEL
argparsecfg-0.2.4.dist-info/top_level.txt
argparsecfg-0.2.4.dist-info/RECORD
