Metadata-Version: 2.1
Name: argparsecfg
Version: 0.2.4
Summary: argparse config.
Home-page: https://github.com/ayasyrev/argparsecfg
Author: Yasyrev Andrei
Author-email: a.yasyrev@gmail.com
License: apache2
Classifier: Programming Language :: Python :: 3
Classifier: Programming Language :: Python :: 3.8
Classifier: Programming Language :: Python :: 3.9
Classifier: Programming Language :: Python :: 3.10
Classifier: Programming Language :: Python :: 3.11
Classifier: Programming Language :: Python :: 3.12
Classifier: License :: OSI Approved :: Apache Software License
Classifier: Operating System :: OS Independent
Requires-Python: >=3.8
License-File: LICENSE
Provides-Extra: test
